terryann_cli/__init__.py
terryann_cli/action_words.py
terryann_cli/auth.py
terryann_cli/client.py
terryann_cli/config.py
terryann_cli/main.py
terryann_cli/spinner.py
terryann_cli/splash.py
terryann_cli/assets/terryann-logo.png
terryann_cli/assets/terryann-logo.svg
terryann_cli/commands/__init__.py
terryann_cli/commands/auth.py
terryann_cli/commands/chat.py
terryann_cli/commands/journeys.py
terryann_cli/commands/status.py
terryann_cli-0.5.2.dist-info/METADATA
terryann_cli-0.5.2.dist-info/WHEEL
terryann_cli-0.5.2.dist-info/entry_points.txt
terryann_cli-0.5.2.dist-info/RECORD
