Metadata-Version: 2.4
Name: terryann-cli
Version: 0.5.2
Summary: CLI for TerryAnn Medicare Journey Intelligence Platform
Author-email: Adam Bell <adambell@gmail.com>
License-Expression: MIT
Requires-Python: >=3.11
Requires-Dist: httpx>=0.27.0
Requires-Dist: prompt-toolkit>=3.0.0
Requires-Dist: rich>=13.0.0
Requires-Dist: supabase>=2.0.0
Requires-Dist: tomli>=2.0.0; python_version < '3.11'
Requires-Dist: typer>=0.9.0
Provides-Extra: dev
Requires-Dist: pytest-asyncio>=0.23.0; extra == 'dev'
Requires-Dist: pytest>=8.0.0; extra == 'dev'
Requires-Dist: ruff>=0.3.0; extra == 'dev'
